fipt/__init__.py
fipt/__main__.py
fipt/helpers.py
fipt/impedance_data.py
fipt/main_logging.py
fipt/plotting.py
fipt-0.3.0.dist-info/LICENSE
fipt-0.3.0.dist-info/METADATA
fipt-0.3.0.dist-info/WHEEL
fipt-0.3.0.dist-info/top_level.txt
fipt-0.3.0.dist-info/RECORD
