Metadata-Version: 2.1
Name: fipt
Version: 0.3.0
Summary: A python module to analyze fast impedance tortuosity measurements.
Home-page: https://github.com/deniz195/fipt-analysis
Author: Deniz Bozyigit
Author-email: deniz195@gmail.com
License: MIT
Platform: UNKNOWN
Classifier: Development Status :: 4 - Beta
Classifier: Intended Audience :: Developers
Classifier: License :: OSI Approved :: MIT License
Classifier: Programming Language :: Python :: 3
Classifier: Programming Language :: Python :: 3.6
Classifier: Programming Language :: Python :: 3.7
Requires-Dist: lmfit (>=1.0.0)
Requires-Dist: numpy (>=1.16.5)
Requires-Dist: scipy (>=1.3.1)
Provides-Extra: dev
Requires-Dist: pandas (>=0.25.1); extra == 'dev'
Requires-Dist: matplotlib (>=3.0.0); extra == 'dev'
Requires-Dist: pytest (>=5.2.1); extra == 'dev'
Provides-Extra: full
Requires-Dist: pandas (>=0.25.1); extra == 'full'
Requires-Dist: matplotlib (>=3.0.0); extra == 'full'
